HISTORY.rst
MANIFEST.in
README.rst
setup.py
adnpy/__init__.py
adnpy/api.py
adnpy/consts.py
adnpy/cursor.py
adnpy/errors.py
adnpy/models.py
adnpy/stream.py
adnpy/utils.py
adnpy.egg-info/PKG-INFO
adnpy.egg-info/SOURCES.txt
adnpy.egg-info/dependency_links.txt
adnpy.egg-info/requires.txt
adnpy.egg-info/top_level.txt
adnpy.egg-info/zip-safe
adnpy/recipes/__init__.py
adnpy/recipes/broadcast.py
examples/send-broadcast.py