Metadata-Version: 1.0
Name: adnpy
Version: 0.3.6
Summary: App.net API library for python
Home-page: http://github.com/appdotnet/adnpy
Author: Alex Kessinger, Bryan Berg, App.net
Author-email: alex@app.net
License: MIT
Keywords: app.net api library
Platform: UNKNOWN
